{
  "_fv": 66,
  "_type": "tool",
  "definition": {
    "toolType": "MultiTool",
    "renderType": 0,
    "blockingRenderType": 0,
    "texture": "potg_of_4",
    "customModelName": "Normal",
    "blockingModelName": "Normal blocking",
    "name": "Pickaxe of the gods",
    "specialInformation": {
      "fixedValue": [
        "Level 4"
      ]
    },
    "creativeTabs": [
      {
        "value": "CUSTOM:Pickaxeofgodstab"
      }
    ],
    "efficiency": 8.0,
    "attackSpeed": 1.5,
    "enchantability": 10,
    "damageVsEntity": 4.0,
    "usageCount": 0,
    "repairItems": [],
    "immuneToFire": false,
    "blockDropsTier": "DIAMOND",
    "blocksAffected": [],
    "stayInGridWhenCrafting": false,
    "damageOnCrafting": false,
    "onItemInUseTick": {
      "name": "Moucepotg"
    },
    "onBlockDestroyedWithTool": {
      "name": "Upgradepotgv2"
    }
  }
}